odoo10_addon_connector_base_product-10.0.1.0.0-py2.7-nspkg.pth
odoo/addons/connector_base_product/__init__.py
odoo/addons/connector_base_product/__manifest__.py
odoo/addons/connector_base_product/i18n/ca.po
odoo/addons/connector_base_product/i18n/de.po
odoo/addons/connector_base_product/i18n/es.po
odoo/addons/connector_base_product/i18n/fr.po
odoo/addons/connector_base_product/i18n/hu.po
odoo/addons/connector_base_product/i18n/it.po
odoo/addons/connector_base_product/i18n/nl.po
odoo/addons/connector_base_product/i18n/pt_BR.po
odoo/addons/connector_base_product/i18n/sl.po
odoo/addons/connector_base_product/i18n/zh_CN.po
odoo/addons/connector_base_product/views/product_view.xml
odoo10_addon_connector_base_product-10.0.1.0.0.dist-info/DESCRIPTION.rst
odoo10_addon_connector_base_product-10.0.1.0.0.dist-info/METADATA
odoo10_addon_connector_base_product-10.0.1.0.0.dist-info/RECORD
odoo10_addon_connector_base_product-10.0.1.0.0.dist-info/WHEEL
odoo10_addon_connector_base_product-10.0.1.0.0.dist-info/metadata.json
odoo10_addon_connector_base_product-10.0.1.0.0.dist-info/namespace_packages.txt
odoo10_addon_connector_base_product-10.0.1.0.0.dist-info/top_level.txt
